<lcgdict>
  <class name="FWWebEventItem"/>
  <class name="FW2GUI"/>
  <class name="FW2Main"/>
  <class name="FW2TEventList"/>
  <class name="FWWebGUIEventFilter"/>
  <class name="FWViewEnergyScale"/>
  <class name="FWWebInvMassDialog"/>
  <class name="FWEveAssociation"/>
  <class name="FWBoxSet"/>
  <class name="FWWebTriggerTable"/>
  <class name="FWWebBoolParameterSetter"/>
  <class name="FWWebLongParameterSetter"/>
  <class name="FWWebDoubleParameterSetter"/>
  <class name="FW3DViewGeometry"/>
  <class name="FWRPZViewGeometry"/>
  <class name="FW3DView"/>
  <class name="FWWebTableView"/>
  <class name="FWWebTriggerTableView"/>
  <class name="FWLegoView"/>
  <class name="FWRPZView"/>
</lcgdict>
